aiohttp_init/__init__.py
aiohttp_init/command.py
aiohttp_init/core/__init__.py
aiohttp_init/core/initialize.py
aiohttp_init/logger/__init__.py
aiohttp_init-0.0.1.dist-info/METADATA
aiohttp_init-0.0.1.dist-info/WHEEL
aiohttp_init-0.0.1.dist-info/entry_points.txt
aiohttp_init-0.0.1.dist-info/top_level.txt
aiohttp_init-0.0.1.dist-info/zip-safe
aiohttp_init-0.0.1.dist-info/RECORD
