Metadata-Version: 2.1
Name: aiohttp-init
Version: 0.0.1
Summary: Aiohttp officially recommends automatic generation libraries
Home-page: UNKNOWN
Author: lateautumn4lin
Author-email: linhanqiu1123@163.com
License: MIT
Keywords: Aiohttp Officially
Platform: UNKNOWN
Requires-Python: >=3
Requires-Dist: certifi (==2019.9.11)
Requires-Dist: colorama (==0.4.1)
Requires-Dist: Jinja2 (==2.10.3)
Requires-Dist: loguru (==0.3.2)
